aron_gen/__init__.py
aron_gen/__main__.py
aron_gen/cli.py
aron_gen/core/AronsonSequence.py
aron_gen/core/AronsonSet.py
aron_gen/core/__init__.py
aron_gen-0.1.7.dist-info/METADATA
aron_gen-0.1.7.dist-info/WHEEL
aron_gen-0.1.7.dist-info/entry_points.txt
aron_gen-0.1.7.dist-info/top_level.txt
aron_gen-0.1.7.dist-info/RECORD
