Metadata-Version: 2.4
Name: aron_gen
Version: 0.1.7
Summary: Generates and verifies Aronson sequences
Author-email: Ido Akov <ido.akov1@alumni.aalto.fi>
License: MIT
Project-URL: Homepage, https://github.com/ikavodo/aron_gen
Project-URL: Repository, https://github.com/ikavodo/aron_gen
Project-URL: Issues, https://github.com/ikavodo/aron_gen/issues
Classifier: Programming Language :: Python :: 3
Classifier: License :: OSI Approved :: MIT License
Classifier: Operating System :: OS Independent
Requires-Python: >=3.8
Requires-Dist: colorama==0.4.6
Requires-Dist: docopt==0.6.2
Requires-Dist: exceptiongroup==1.2.2
Requires-Dist: iniconfig==2.1.0
Requires-Dist: num2words==0.5.14
Requires-Dist: packaging==24.2
Requires-Dist: pluggy==1.5.0
Requires-Dist: pytest==8.3.5
Requires-Dist: tomli==2.2.1
